aimrecords/__init__.py
aimrecords/__version__.py
aimrecords/reader.py
aimrecords/writer.py
aim_records-0.0.1.dist-info/LICENSE
aim_records-0.0.1.dist-info/METADATA
aim_records-0.0.1.dist-info/WHEEL
aim_records-0.0.1.dist-info/top_level.txt
aim_records-0.0.1.dist-info/RECORD
